PoissonFC/FCDirichlet.py
PoissonFC/FCsemomega.py
PoissonFC/FuncaoCorrente.py
PoissonFC/FuncaoCorrenteCC.py
PoissonFC/__init__.py
PoissonFC-0.0.1.dist-info/LICENSE
PoissonFC-0.0.1.dist-info/METADATA
PoissonFC-0.0.1.dist-info/WHEEL
PoissonFC-0.0.1.dist-info/top_level.txt
PoissonFC-0.0.1.dist-info/RECORD
