Metadata-Version: 2.1
Name: PoissonFC
Version: 0.0.1
Summary: Um pacote para o calculo da funcao corrente
Home-page: UNKNOWN
Author: Lucas Salimene
Author-email: lucassalimene@protonmail.com
License: MIT
Platform: UNKNOWN
Requires-Python: >=3.8
License-File: LICENSE
Requires-Dist: numpy
